[
    {
        "Match ID": "12436501",
        "Round": "13",
        "Status": "Ended",
        "Start Timestamp": "1732906800",
        "Home Team": "Brighton & Hove Albion",
        "Away Team": "Southampton",
        "Home Score": "2",
        "Away Score": "1",
        "Final Result Only": "True",
        "Has XG Data": "False",
        "Slug": "southampton-brighton-and-hove-albion"
    },
    {
        "Match ID": "12436500",
        "Round": "13",
        "Status": "Ended",
        "Start Timestamp": "1732986000",
        "Home Team": "Brentford",
        "Away Team": "Leicester City",
        "Home Score": "4",
        "Away Score": "2",
        "Final Result Only": "True",
        "Has XG Data": "True",
        "Slug": "brentford-leicester-city"
    },
    {
        "Match ID": "12436502",
        "Round": "13",
        "Status": "Ended",
        "Start Timestamp": "1732971600",
        "Home Team": "Crystal Palace",
        "Away Team": "Newcastle United",
        "Home Score": "2",
        "Away Score": "1",
        "Final Result Only": "False",
        "Has XG Data": "False",
        "Slug": "newcastle-united-crystal-palace"
    },
    {
        "Match ID": "12436503",
        "Round": "13",
        "Status": "Ended",
        "Start Timestamp": "1732978800",
        "Home Team": "Nottingham Forest",
        "Away Team": "Ipswich Town",
        "Home Score": "2",
        "Away Score": "1",
        "Final Result Only": "True",
        "Has XG Data": "True",
        "Slug": "ipswich-town-nottingham-forest"
    },
    {
        "Match ID": "12436922",
        "Round": "13",
        "Status": "Ended",
        "Start Timestamp": "1732985100",
        "Home Team": "Wolverhampton",
        "Away Team": "Bournemouth",
        "Home Score": "2",
        "Away Score": "4",
        "Final Result Only": "False",
        "Has XG Data": "True",
        "Slug": "bournemouth-wolverhampton"
    },
    {
        "Match ID": "12436914",
        "Round": "13",
        "Status": "Ended",
        "Start Timestamp": "1732982400",
        "Home Team": "West Ham United",
        "Away Team": "Arsenal",
        "Home Score": "3",
        "Away Score": "5",
        "Final Result Only": "False",
        "Has XG Data": "False",
        "Slug": "arsenal-west-ham-united"
    },
    {
        "Match ID": "12436498",
        "Round": "13",
        "Status": "Ended",
        "Start Timestamp": "1733055300",
        "Home Team": "Chelsea",
        "Away Team": "Aston Villa",
        "Home Score": "4",
        "Away Score": "0",
        "Final Result Only": "False",
        "Has XG Data": "False",
        "Slug": "aston-villa-chelsea"
    },
    {
        "Match ID": "12436505",
        "Round": "13",
        "Status": "Ended",
        "Start Timestamp": "1733065200",
        "Home Team": "Manchester United",
        "Away Team": "Everton",
        "Home Score": "4",
        "Away Score": "1",
        "Final Result Only": "False",
        "Has XG Data": "True",
        "Slug": "everton-manchester-united"
    },
    {
        "Match ID": "12436507",
        "Round": "13",
        "Status": "Ended",
        "Start Timestamp": "1733059800",
        "Home Team": "Tottenham Hotspur",
        "Away Team": "Fulham",
        "Home Score": "1",
        "Away Score": "2",
        "Final Result Only": "False",
        "Has XG Data": "False",
        "Slug": "fulham-tottenham-hotspur"
    },
    {
        "Match ID": "12436504",
        "Round": "13",
        "Status": "Ended",
        "Start Timestamp": "1733076900",
        "Home Team": "Liverpool",
        "Away Team": "Manchester City",
        "Home Score": "3",
        "Away Score": "1",
        "Final Result Only": "True",
        "Has XG Data": "False",
        "Slug": "liverpool-manchester-city"
    }
]